nr/__init__.py
nr/optional/__init__.py
nr/optional/py.typed
nr.optional-0.1.1.dist-info/LICENSE.txt
nr.optional-0.1.1.dist-info/METADATA
nr.optional-0.1.1.dist-info/WHEEL
nr.optional-0.1.1.dist-info/top_level.txt
nr.optional-0.1.1.dist-info/RECORD
