Metadata-Version: 2.1
Name: nr.optional
Version: 0.1.1
Summary: Package description here.
Home-page: https://git.niklasrosenstein.com/NiklasRosenstein/nr
Author: Niklas Rosenstein
Author-email: rosensteinniklas@gmail.com
License: MIT
Platform: UNKNOWN
Requires-Python: >=3.5.0,<4.0.0
